peft/__init__.py
peft/auto.py
peft/config.py
peft/helpers.py
peft/import_utils.py
peft/mapping.py
peft/mapping_func.py
peft/mixed_model.py
peft/peft_model.py
peft/py.typed
peft/optimizers/__init__.py
peft/optimizers/loraplus.py
peft/tuners/__init__.py
peft/tuners/_buffer_dict.py
peft/tuners/lycoris_utils.py
peft/tuners/tuners_utils.py
peft/tuners/adalora/__init__.py
peft/tuners/adalora/bnb.py
peft/tuners/adalora/config.py
peft/tuners/adalora/gptq.py
peft/tuners/adalora/layer.py
peft/tuners/adalora/model.py
peft/tuners/adaption_prompt/__init__.py
peft/tuners/adaption_prompt/config.py
peft/tuners/adaption_prompt/layer.py
peft/tuners/adaption_prompt/model.py
peft/tuners/adaption_prompt/utils.py
peft/tuners/boft/__init__.py
peft/tuners/boft/config.py
peft/tuners/boft/layer.py
peft/tuners/boft/model.py
peft/tuners/boft/fbd/__init__.py
peft/tuners/boft/fbd/fbd_cuda.cpp
peft/tuners/boft/fbd/fbd_cuda_kernel.cu
peft/tuners/bone/__init__.py
peft/tuners/bone/config.py
peft/tuners/bone/layer.py
peft/tuners/bone/model.py
peft/tuners/cpt/__init__.py
peft/tuners/cpt/config.py
peft/tuners/cpt/model.py
peft/tuners/fourierft/__init__.py
peft/tuners/fourierft/config.py
peft/tuners/fourierft/layer.py
peft/tuners/fourierft/model.py
peft/tuners/hra/__init__.py
peft/tuners/hra/config.py
peft/tuners/hra/layer.py
peft/tuners/hra/model.py
peft/tuners/ia3/__init__.py
peft/tuners/ia3/bnb.py
peft/tuners/ia3/config.py
peft/tuners/ia3/layer.py
peft/tuners/ia3/model.py
peft/tuners/ln_tuning/__init__.py
peft/tuners/ln_tuning/config.py
peft/tuners/ln_tuning/layer.py
peft/tuners/ln_tuning/model.py
peft/tuners/loha/__init__.py
peft/tuners/loha/config.py
peft/tuners/loha/layer.py
peft/tuners/loha/model.py
peft/tuners/lokr/__init__.py
peft/tuners/lokr/config.py
peft/tuners/lokr/layer.py
peft/tuners/lokr/model.py
peft/tuners/lora/__init__.py
peft/tuners/lora/aqlm.py
peft/tuners/lora/awq.py
peft/tuners/lora/bnb.py
peft/tuners/lora/config.py
peft/tuners/lora/corda.py
peft/tuners/lora/dora.py
peft-0.15.0.dist-info/LICENSE
peft-0.15.0.dist-info/METADATA
peft-0.15.0.dist-info/WHEEL
peft-0.15.0.dist-info/top_level.txt
peft-0.15.0.dist-info/RECORD
