Metadata-Version: 2.2
Name: peft
Version: 0.15.0
Summary: Parameter-Efficient Fine-Tuning (PEFT)
Home-page: https://github.com/huggingface/peft
Author: The HuggingFace team
Author-email: benjamin@huggingface.co
License: Apache
Keywords: deep learning
Classifier: Development Status :: 5 - Production/Stable
Classifier: Intended Audience :: Developers
Classifier: Intended Audience :: Education
Classifier: Intended Audience :: Science/Research
Classifier: License :: OSI Approved :: Apache Software License
Classifier: Operating System :: OS Independent
Classifier: Programming Language :: Python :: 3
Classifier: Programming Language :: Python :: 3.9
Classifier: Programming Language :: Python :: 3.10
Classifier: Programming Language :: Python :: 3.11
Classifier: Programming Language :: Python :: 3.12
Classifier: Topic :: Scientific/Engineering :: Artificial Intelligence
Requires-Python: >=3.9.0
License-File: LICENSE
Requires-Dist: numpy>=1.17
Requires-Dist: packaging>=20.0
Requires-Dist: psutil
Requires-Dist: pyyaml
Requires-Dist: torch>=1.13.0
Requires-Dist: transformers
Requires-Dist: tqdm
Requires-Dist: accelerate>=0.21.0
Requires-Dist: safetensors
Requires-Dist: huggingface_hub>=0.25.0
Provides-Extra: quality
Requires-Dist: black; extra == "quality"
Requires-Dist: hf-doc-builder; extra == "quality"
Requires-Dist: ruff~=0.9.2; extra == "quality"
Provides-Extra: docs-specific
Requires-Dist: black; extra == "docs-specific"
Requires-Dist: hf-doc-builder; extra == "docs-specific"
Provides-Extra: dev
Requires-Dist: black; extra == "dev"
Requires-Dist: hf-doc-builder; extra == "dev"
Requires-Dist: ruff~=0.9.2; extra == "dev"
Requires-Dist: black; extra == "dev"
Requires-Dist: hf-doc-builder; extra == "dev"
Provides-Extra: test
Requires-Dist: black; extra == "test"
Requires-Dist: hf-doc-builder; extra == "test"
Requires-Dist: ruff~=0.9.2; extra == "test"
Requires-Dist: black; extra == "test"
Requires-Dist: hf-doc-builder; extra == "test"
Requires-Dist: pytest; extra == "test"
Requires-Dist: pytest-cov; extra == "test"
Requires-Dist: pytest-xdist; extra == "test"
Requires-Dist: parameterized; extra == "test"
Requires-Dist: datasets; extra == "test"
Requires-Dist: diffusers; extra == "test"
Requires-Dist: scipy; extra == "test"
Requires-Dist: protobuf; extra == "test"
Requires-Dist: sentencepiece; extra == "test"
Dynamic: author
Dynamic: author-email
Dynamic: classifier
Dynamic: description
Dynamic: description-content-type
Dynamic: home-page
Dynamic: keywords
Dynamic: license
Dynamic: provides-extra
Dynamic: requires-dist
Dynamic: requires-python
Dynamic: summary
